AUTHORS.txt
CHANGES.txt
LICENSE.txt
MANIFEST.in
README.rst
requirements.txt
setup.py
varnish_bans_manager/__init__.py
varnish_bans_manager/assets_mapping.py
varnish_bans_manager/celery_app.py
varnish_bans_manager/runner.py
varnish_bans_manager/settings.py
varnish_bans_manager/urls.py
varnish_bans_manager/wsgi.py
varnish_bans_manager.egg-info/PKG-INFO
varnish_bans_manager.egg-info/SOURCES.txt
varnish_bans_manager.egg-info/dependency_links.txt
varnish_bans_manager.egg-info/entry_points.txt
varnish_bans_manager.egg-info/requires.txt
varnish_bans_manager.egg-info/top_level.txt
varnish_bans_manager/assets/bootstrap--en-8a6fc5cea96ef48a716b81de01cd46a956e9e62e.js
varnish_bans_manager/assets/bootstrap--es-098e9a1e3341d52523beea59ed09aa26edc94e49.js
varnish_bans_manager/assets/bundle-2422d7a23e73fbe5bd8156b1b366c3413550f947.css
varnish_bans_manager/assets/bundle-26b75b7acbacf7075eaa703aa982401e4814becd.js
varnish_bans_manager/assets/favicon-908651f9d78cd5064750219a970d26d546172109.ico
varnish_bans_manager/assets/varnish-bans-manager/fonts/Ubuntu-Medium-webfont-19bef830aba0fca66525a6c3fb19033e558fd566.woff
varnish_bans_manager/assets/varnish-bans-manager/fonts/Ubuntu-Medium-webfont-5e59848a163fb8a4a8a38379a1615a1ae035640f.ttf
varnish_bans_manager/assets/varnish-bans-manager/fonts/Ubuntu-Medium-webfont-72cd431c64c6df1b2a7f664d53416a58f58eb7f3.eot
varnish_bans_manager/assets/varnish-bans-manager/fonts/Ubuntu-Medium-webfont-fe9ebe1bb06e9e2add26ecd9687554320eac0262.svg
varnish_bans_manager/assets/varnish-bans-manager/fonts/Ubuntu-Regular-webfont-0cac9fe6b49948a9f4ccde332465a6db83f6b38f.ttf
varnish_bans_manager/assets/varnish-bans-manager/fonts/Ubuntu-Regular-webfont-4f5c8acb8065aee54659fcf7201aa50adfb842d8.woff
varnish_bans_manager/assets/varnish-bans-manager/fonts/Ubuntu-Regular-webfont-5936977660e6aa4f5df80b4afec7d0b36632492c.eot
varnish_bans_manager/assets/varnish-bans-manager/fonts/Ubuntu-Regular-webfont-bb74d56f4899de902002033f1cadf08346a9ae3c.svg
varnish_bans_manager/assets/varnish-bans-manager/fonts/fontawesome-webfont-1f0bdc58aa59ab954ce78a94e4d0ea94ab436554.woff
varnish_bans_manager/assets/varnish-bans-manager/fonts/fontawesome-webfont-b4fb88f37b50e10fdcff849d236123500242dd6a.svg
