Metadata-Version: 1.1
Name: varnish-bans-manager
Version: 0.6.1
Summary: Varnish Bans Manager.
Home-page: https://github.com/allenta/varnish-bans-manager
Author: Allenta Consulting
Author-email: info@allenta.com
License: GPL
Platform: UNKNOWN
Classifier: Framework :: Django
Classifier: Intended Audience :: Developers
Classifier: Intended Audience :: System Administrators
Classifier: Operating System :: OS Independent
